state_machine_py/__init__.py
state_machine_py/abstract_state.py
state_machine_py/const_py_generator_v17.py
state_machine_py/graph_generator.py
state_machine_py/intermachine.py
state_machine_py/main_finally.py
state_machine_py/multiple_state_machine.py
state_machine_py/request.py
state_machine_py/state_machine.py
state_machine_py/state_machine_helper.py
state_machine_py/state_py_generator_v18.py
state_machine_py/transition_py_maker.py
state_machine_py/code_gen/__init__.py
state_machine_py/code_gen/const_file_gen_v17.py
state_machine_py/code_gen/const_py_gen_v22.py
state_machine_py/code_gen/const_stringification_v17.py
state_machine_py/code_gen/directive_edge_v15n2.py
state_machine_py/code_gen/file_io_v11n80.py
state_machine_py/code_gen/json_reader_v11n100.py
state_machine_py/code_gen/state_file_gen_v18.py
state_machine_py/code_gen/state_files_gen_v18.py
state_machine_py/code_gen/toml_reader_v11n90.py
state_machine_py/code_gen/transition_conf_py_stringification_v21.py
state_machine_py/code_gen/transition_conf_v15.py
state_machine_py/code_gen/transition_conf_v16n2.py
state_machine_py/code_gen/transition_conf_v16n3.py
state_machine_py/code_gen/py_syntax/__init__.py
state_machine_py/code_gen/py_syntax/class_gen_v18.py
state_machine_py/code_gen/py_syntax/import_gen_v18.py
state_machine_py/code_gen/py_syntax/method_gen_v18.py
state_machine_py/code_gen/py_syntax/switch_gen_v16n3.py
state_machine_py/conf_obj/__init__.py
state_machine_py/conf_obj/clustered_directive_edge_v15.py
state_machine_py/conf_obj/const_v17.py
state_machine_py/conf_obj/const_v18.py
state_machine_py/conf_obj/directive_edge_v15.py
state_machine_py/conf_obj/transition_v15.py
state_machine_py/conf_obj/transition_v16n2.py
state_machine_py/conf_obj/transition_v16n3.py
state_machine_py/graph_gen/__init__.py
state_machine_py/graph_gen/render_v15.py
state_machine_py/graph_gen/render_v15n2.py
state_machine_py-18.0.29.dist-info/LICENSE
state_machine_py-18.0.29.dist-info/METADATA
state_machine_py-18.0.29.dist-info/WHEEL
state_machine_py-18.0.29.dist-info/top_level.txt
state_machine_py-18.0.29.dist-info/RECORD
