Metadata-Version: 2.1
Name: state-machine-py
Version: 18.0.29
Summary: A state diagram machine package
Home-page: https://github.com/muzudho/state-machine-py
Author: muzudho
Author-email: muzudho1@gmail.com
License: UNKNOWN
Project-URL: Bug Tracker, https://github.com/muzudho/state-machine-py/issues
Platform: UNKNOWN
Classifier: Programming Language :: Python :: 3
Classifier: License :: OSI Approved :: MIT License
Classifier: Operating System :: OS Independent
Requires-Python: >=3.6
License-File: LICENSE
